autmeopypi-1.0.0.dist-info/licenses/LICENSE
autopypi/__init__.py
autopypi/bat.py
autopypi/bld.py
autopypi/cfg.py
autopypi/chk.py
autopypi/ci.py
autopypi/cli.py
autopypi/col.py
autopypi/git.py
autopypi/log.py
autopypi/srv.py
autopypi/upl.py
autopypi/utl.py
autopypi/ver.py
autmeopypi-1.0.0.dist-info/METADATA
autmeopypi-1.0.0.dist-info/WHEEL
autmeopypi-1.0.0.dist-info/entry_points.txt
autmeopypi-1.0.0.dist-info/top_level.txt
autmeopypi-1.0.0.dist-info/RECORD
