Metadata-Version: 2.4
Name: autmeopypi
Version: 1.0.0
Summary: Automated Python Package Publishing Tool
Author-email: mero <mero@ps.dev>
Maintainer-email: mero <mero@ps.dev>
License: MIT
Project-URL: Homepage, https://github.com/6x-u/autopypi
Project-URL: Documentation, https://github.com/6x-u/autopypi#readme
Project-URL: Repository, https://github.com/6x-u/autopypi
Project-URL: Issues, https://github.com/6x-u/autopypi/issues
Project-URL: Changelog, https://github.com/6x-u/autopypi/releases
Keywords: pypi,upload,publish,package,build,wheel,sdist,automation,ci,cd,release,distribution
Classifier: Development Status :: 5 - Production/Stable
Classifier: Environment :: Console
Classifier: Environment :: Web Environment
Classifier: Intended Audience :: Developers
Classifier: License :: OSI Approved :: MIT License
Classifier: Operating System :: OS Independent
Classifier: Operating System :: POSIX :: Linux
Classifier: Operating System :: Microsoft :: Windows
Classifier: Operating System :: MacOS
Classifier: Programming Language :: Python :: 3
Classifier: Programming Language :: Python :: 3.7
Classifier: Programming Language :: Python :: 3.8
Classifier: Programming Language :: Python :: 3.9
Classifier: Programming Language :: Python :: 3.10
Classifier: Programming Language :: Python :: 3.11
Classifier: Programming Language :: Python :: 3.12
Classifier: Programming Language :: Python :: 3.13
Classifier: Programming Language :: Python :: 3.14
Classifier: Topic :: Software Development :: Build Tools
Classifier: Topic :: Software Development :: Libraries :: Python Modules
Classifier: Topic :: System :: Software Distribution
Classifier: Topic :: Utilities
Requires-Python: >=3.9
License-File: LICENSE
Requires-Dist: build>=0.7.0
Requires-Dist: twine>=4.0.0
Requires-Dist: wheel>=0.37.0
Requires-Dist: setuptools>=61.0
Requires-Dist: toml>=0.10.0
Requires-Dist: flask>=2.0.0
Provides-Extra: dev
Requires-Dist: pytest>=7.0.0; extra == "dev"
Dynamic: license-file
